README.txt
setup.py
constellations/__init__.py
constellations/config.py
constellations/discovery.py
constellations/ducttape.py
constellations/gossip_node.py
constellations/key_value.py
constellations/key_value_client.py
constellations/message.py
constellations/node.py
constellations/peer_node.py
constellations/socket_transport.py
constellations.egg-info/PKG-INFO
constellations.egg-info/SOURCES.txt
constellations.egg-info/dependency_links.txt
constellations.egg-info/top_level.txt